table_data_process_lib/__init__.py
table_data_process_lib/example/__init__.py
table_data_process_lib/example/example.py
table_data_process_lib/example/example_mlp.py
table_data_process_lib/src/__init__.py
table_data_process_lib/src/classification.py
table_data_process_lib/src/clasterization.py
table_data_process_lib/src/preprocessing.py
table_data_process_lib/src/regression.py
table_data_process_lib-0.1.7.dist-info/METADATA
table_data_process_lib-0.1.7.dist-info/WHEEL
table_data_process_lib-0.1.7.dist-info/top_level.txt
table_data_process_lib-0.1.7.dist-info/RECORD
