Metadata-Version: 2.1
Name: table_data_process_lib
Version: 0.1.7
Summary: Library for table data processing
Home-page: https://github.com/PavelMalyshev01/table_data_process_lib
Author: Pavel Malyshev
Author-email: p.malyshev@razumai.pro
License: MIT
Classifier: Programming Language :: Python :: 3
Classifier: License :: OSI Approved :: MIT License
Classifier: Operating System :: OS Independent
Requires-Python: >=3.6
Requires-Dist: pandas
Requires-Dist: matplotlib
Requires-Dist: seaborn
Requires-Dist: xgboost
Requires-Dist: scikit-learn
Requires-Dist: imblearn
Requires-Dist: pickle
Requires-Dist: lightgbm
